flask_digest_auth/__init__.py
flask_digest_auth/algo.py
flask_digest_auth/auth.py
Flask_DigestAuth-0.7.1.dist-info/LICENSE
Flask_DigestAuth-0.7.1.dist-info/METADATA
Flask_DigestAuth-0.7.1.dist-info/WHEEL
Flask_DigestAuth-0.7.1.dist-info/top_level.txt
Flask_DigestAuth-0.7.1.dist-info/RECORD
