Metadata-Version: 2.1
Name: Flask-DigestAuth
Version: 0.7.1
Summary: The Flask HTTP Digest Authentication project.
Author-email: imacat <imacat@mail.imacat.idv.tw>
Project-URL: Documentation, https://flask-digestauth.readthedocs.io
Project-URL: Change Log, https://mia-accounting.readthedocs.io/en/latest/changelog.html
Project-URL: Repository, https://github.com/imacat/flask-digestauth
Project-URL: Bug Tracker, https://github.com/imacat/flask-digestauth/issues
Keywords: flask,digest-authentication
Classifier: Programming Language :: Python :: 3
Classifier: License :: OSI Approved :: Apache Software License
Classifier: Operating System :: OS Independent
Classifier: Framework :: Flask
Classifier: Topic :: System :: Systems Administration :: Authentication/Directory
Classifier: Intended Audience :: Developers
Requires-Python: >=3.8
License-File: LICENSE
Requires-Dist: Flask
Provides-Extra: devel
Requires-Dist: httpx>=0.20.0; extra == "devel"
